trusttrees/__init__.py
trusttrees/__main__.py
trusttrees/constants.py
trusttrees/dns.py
trusttrees/draw.py
trusttrees/global_state.py
trusttrees/registar_checking.py
trusttrees/usage.py
trusttrees/utils.py
TrustTrees-3.0.3.dist-info/LICENSE
TrustTrees-3.0.3.dist-info/METADATA
TrustTrees-3.0.3.dist-info/WHEEL
TrustTrees-3.0.3.dist-info/entry_points.txt
TrustTrees-3.0.3.dist-info/top_level.txt
TrustTrees-3.0.3.dist-info/RECORD
