Metadata-Version: 2.1
Name: TrustTrees
Version: 3.0.3
Summary: A Tool for DNS Delegation Trust Graphing
Home-page: https://github.com/mandatoryprogrammer/TrustTrees
Author: mandatoryprogrammer
Author-email: UNKNOWN
License: UNKNOWN
Keywords: subdomain,subdomain-takeover,dns,dnssec,security,bug-bounty,bugbounty
Platform: UNKNOWN
Requires-Dist: boto3 (==1.9.227)
Requires-Dist: dnsimple (==2.0.0)
Requires-Dist: dnspython (==1.16.0)
Requires-Dist: pygraphviz (==1.5)
Requires-Dist: requests (==2.22.0)
Requires-Dist: tldextract (==2.2.1)
